Metadata-Version: 1.0
Name: yg
Version: 0.1.0
Summary: A set of misc func by yg.
Home-page: http://github.com/gyang274/yg
Author: Guang Yang
Author-email: gyang274@gmail.com
License: MIT
Platform: UNKNOWN
